yta_audio_narration/__init__.py
yta_audio_narration/enums.py
yta_audio_narration/narrator.py
yta_audio_narration/voices/__init__.py
yta_audio_narration/voices/coqui.py
yta_audio_narration/voices/google.py
yta_audio_narration/voices/microsoft.py
yta_audio_narration/voices/open_voice.py
yta_audio_narration/voices/tetyys.py
yta_audio_narration/voices/tiktok.py
yta_audio_narration/voices/tortoise.py
yta_audio_narration/voices/ttsmp3.py
yta_audio_narration-0.0.11.dist-info/LICENSE
yta_audio_narration-0.0.11.dist-info/METADATA
yta_audio_narration-0.0.11.dist-info/WHEEL
yta_audio_narration-0.0.11.dist-info/RECORD
