Metadata-Version: 2.3
Name: yta-audio-narration
Version: 0.0.11
Summary: Youtube Autonomous Audio Narration Module.
Author: danialcala94
Author-email: danielalcalavalera@gmail.com
Requires-Python: ==3.9
Classifier: Programming Language :: Python :: 3
Classifier: Programming Language :: Python :: 3.9
Requires-Dist: yta_audio_narration_common (>=0.0.1,<1.0.0)
Requires-Dist: yta_audio_narration_coqui (>=0.0.1,<1.0.0)
Requires-Dist: yta_audio_narration_google (>=0.0.1,<1.0.0)
Requires-Dist: yta_audio_narration_microsoft (>=0.0.1,<1.0.0)
Requires-Dist: yta_audio_narration_open_voice (>=0.0.1,<1.0.0)
Requires-Dist: yta_audio_narration_tetyys (>=0.0.1,<1.0.0)
Requires-Dist: yta_audio_narration_tiktok (>=0.0.1,<1.0.0)
Requires-Dist: yta_audio_narration_tortoise (>=0.0.1,<1.0.0)
Requires-Dist: yta_audio_narration_ttsmp3 (>=0.0.1,<1.0.0)
Requires-Dist: yta_constants (>=0.0.1,<1.0.0)
Requires-Dist: yta_programming (>=0.0.1,<1.0.0)
Requires-Dist: yta_validation (>=0.0.1,<1.0.0)
